durable_dot_dict/__init__.py
durable_dot_dict/collection.py
durable_dot_dict/dot.py
durable_dot_dict/dotdict.py
durable_dot_dict-0.0.21.dist-info/METADATA
durable_dot_dict-0.0.21.dist-info/WHEEL
durable_dot_dict-0.0.21.dist-info/top_level.txt
durable_dot_dict-0.0.21.dist-info/RECORD
