Metadata-Version: 2.4
Name: durable_dot_dict
Version: 0.0.21
Summary: Durable Dot Dictionary
Author: Risto Kowaczewski
Keywords: durable_dot_dict
Classifier: Programming Language :: Python :: 3
Classifier: License :: OSI Approved :: MIT License
Classifier: Operating System :: OS Independent
Requires-Python: >=3.10
Requires-Dist: dotdict_parser
Dynamic: author
Dynamic: classifier
Dynamic: description
Dynamic: description-content-type
Dynamic: keywords
Dynamic: requires-dist
Dynamic: requires-python
Dynamic: summary
